o2security/__init__.py
o2security/core.py
o2security/tokman.py
o2security/ai/__init__.py
o2security/ai/client.py
o2security/ai/memory.py
o2security-0.2.0.dist-info/licenses/LICENSE
webapp/__init__.py
webapp/app.py
webapp/cli.py
webapp/templates/ai_dashboard.html
webapp/templates/ai_project_view.html
webapp/templates/index.html
webapp/templates/project.html
o2security-0.2.0.dist-info/METADATA
o2security-0.2.0.dist-info/WHEEL
o2security-0.2.0.dist-info/entry_points.txt
o2security-0.2.0.dist-info/top_level.txt
o2security-0.2.0.dist-info/RECORD
