Metadata-Version: 2.4
Name: o2security
Version: 0.2.0
Summary: A simple library for securely managing tokens and secrets.
Home-page: https://github.com/unknownmsv/o2security
Author: sina
Author-email: sina@unknownmsv.ir
Classifier: Programming Language :: Python :: 3
Classifier: License :: OSI Approved :: MIT License
Classifier: Operating System :: OS Independent
Requires-Python: >=3.7
License-File: LICENSE
Requires-Dist: cryptography
Requires-Dist: python-dotenv
Requires-Dist: Flask
Dynamic: author
Dynamic: author-email
Dynamic: classifier
Dynamic: description
Dynamic: description-content-type
Dynamic: home-page
Dynamic: license-file
Dynamic: requires-dist
Dynamic: requires-python
Dynamic: summary
